dictionary/__init__.py
dictionary/dictionary.py
ekg_cs458_dict-0.0.3.dist-info/METADATA
ekg_cs458_dict-0.0.3.dist-info/WHEEL
ekg_cs458_dict-0.0.3.dist-info/top_level.txt
ekg_cs458_dict-0.0.3.dist-info/RECORD
