Metadata-Version: 2.1
Name: ekg-cs458-dict
Version: 0.0.3
Summary: A package for my CS453 Homework 1.
Author: Ege Kaan Gürkan
License: UNKNOWN
Platform: UNKNOWN
Requires-Python: >=3.8
Requires-Dist: requests (>=2.23.0)
